_jsonata.cp37-win_amd64.pyd
jsonata/__init__.py
jsonata-0.2.5.dist-info/METADATA
jsonata-0.2.5.dist-info/WHEEL
jsonata-0.2.5.dist-info/top_level.txt
jsonata-0.2.5.dist-info/RECORD
